innertube_de/__init__.py
innertube_de/containers.py
innertube_de/endpoints.py
innertube_de/errors.py
innertube_de/extractor.py
innertube_de/itags.py
innertube_de/items.py
innertube_de/stream.py
innertube_de/types.py
innertube_de/utils.py
innertube_de-1.0.0.post0.dist-info/LICENSE
innertube_de-1.0.0.post0.dist-info/METADATA
innertube_de-1.0.0.post0.dist-info/WHEEL
innertube_de-1.0.0.post0.dist-info/top_level.txt
innertube_de-1.0.0.post0.dist-info/RECORD
