Metadata-Version: 2.1
Name: innertube-de
Version: 1.0.0.post0
Summary: InnerTube Data Extractor
Home-page: https://github.com/g3nsy/innertube-de
Author: g3nsy
Author-email: g3nsydev@gmail.com
License: MIT
Classifier: License :: OSI Approved :: MIT License
Classifier: Programming Language :: Python :: 3
Requires-Python: >=3.6.0
License-File: LICENSE
